hzclient/__init__.py
hzclient/client.py
hzclient/constants.py
hzclient/duel_utils.py
hzclient/exceptions.py
hzclient/session.py
hzclient/state.py
hzclient/utils.py
hzclient/_vendor/engineio_v3/__init__.py
hzclient/_vendor/engineio_v3/engineio/__init__.py
hzclient/_vendor/engineio_v3/engineio/client.py
hzclient/_vendor/engineio_v3/engineio/exceptions.py
hzclient/_vendor/engineio_v3/engineio/json.py
hzclient/_vendor/engineio_v3/engineio/packet.py
hzclient/_vendor/engineio_v3/engineio/payload.py
hzclient/_vendor/socketio_v4/__init__.py
hzclient/_vendor/socketio_v4/socketio/__init__.py
hzclient/_vendor/socketio_v4/socketio/client.py
hzclient/_vendor/socketio_v4/socketio/exceptions.py
hzclient/_vendor/socketio_v4/socketio/namespace.py
hzclient/_vendor/socketio_v4/socketio/packet.py
hzclient/enums/__init__.py
hzclient/enums/gender_type.py
hzclient/enums/training_type.py
hzclient/models/__init__.py
hzclient/models/ad_info.py
hzclient/models/base.py
hzclient/models/base_character.py
hzclient/models/character.py
hzclient/models/config.py
hzclient/models/extended_config.py
hzclient/models/hideout.py
hzclient/models/hideout_room.py
hzclient/models/opponent.py
hzclient/models/quest.py
hzclient/models/response.py
hzclient/models/training.py
hzclient/models/training_quest.py
hzclient/models/treasure_event.py
hzclient/models/user.py
hzclient/models/voucher.py
hzclient/models/guild/__init__.py
hzclient/models/guild/guild_log.py
hzclient/models/guild/guild_log_entry.py
hzclient-0.2.8.dist-info/METADATA
hzclient-0.2.8.dist-info/WHEEL
hzclient-0.2.8.dist-info/top_level.txt
hzclient-0.2.8.dist-info/RECORD
