Metadata-Version: 2.4
Name: hzclient
Version: 0.2.8
Summary: A client library for interacting with the HeroZero game API
Author: Curvu
Project-URL: Homepage, https://github.com/HZPilot/hzclient
Requires-Python: >=3.10
Requires-Dist: pydantic>=2.12.4
Requires-Dist: curl-cffi>=0.13.0
Requires-Dist: jsonmerge>=1.9.2
Requires-Dist: jsonschema<4.18
Requires-Dist: six>=1.17.0
Requires-Dist: websocket-client>=1.9.0
